toybox/__about__.py
toybox/__init__.py
toybox/__main__.py
toybox/boxfile.py
toybox/dependency.py
toybox/exceptions.py
toybox/files.py
toybox/git.py
toybox/paths.py
toybox/toybox.py
toybox/toystore.py
toybox/url.py
toybox/utils.py
toybox/version.py
toyboxpy-1.4.0.dist-info/METADATA
toyboxpy-1.4.0.dist-info/WHEEL
toyboxpy-1.4.0.dist-info/entry_points.txt
toyboxpy-1.4.0.dist-info/licenses/LICENSE
toyboxpy-1.4.0.dist-info/RECORD
