Metadata-Version: 2.4
Name: toyboxpy
Version: 1.4.0
Summary: A Lua, C and asset dependency manager for the Playdate SDK
Project-URL: Homepage, https://code.malenfant.net/didier/toybox.py
Project-URL: Documentation, https://code.malenfant.net/didier/toybox.py#readme
Project-URL: Bug Tracker, https://code.malenfant.net/didier/toybox.py/issues
Project-URL: Source Code, https://code.malenfant.net/didier/toybox.py
Author-email: Didier Malenfant <coding@malenfant.net>
License-Expression: MIT
License-File: LICENSE
Keywords: package,package management,playdate
Classifier: Development Status :: 5 - Production/Stable
Classifier: Programming Language :: Python
Classifier: Programming Language :: Python :: 3.7
Classifier: Programming Language :: Python :: 3.8
Classifier: Programming Language :: Python :: 3.9
Classifier: Programming Language :: Python :: 3.10
Classifier: Programming Language :: Python :: Implementation :: CPython
Classifier: Programming Language :: Python :: Implementation :: PyPy
Requires-Python: >=3.7
Requires-Dist: semver
Requires-Dist: tomli>=1.1.0; python_version < '3.11'
